{
  "$schema": "https://www.designtokens.org/schemas/2025.10/format.json",
  "$description": "Primitive color scale — OKLCH primary, hex fallback. Never reference directly in components. Use semantic tokens.",
  "color": {
    "$type": "color",
    "neutral": {
      "0":    { "$value": { "colorSpace": "oklch", "components": [1, 0, "none"], "hex": "#ffffff" } },
      "50":   { "$value": { "colorSpace": "oklch", "components": [0.98, 0.003, 247], "hex": "#f8fafc" } },
      "100":  { "$value": { "colorSpace": "oklch", "components": [0.961, 0.007, 247], "hex": "#f1f5f9" } },
      "200":  { "$value": { "colorSpace": "oklch", "components": [0.925, 0.012, 247], "hex": "#e2e8f0" } },
      "300":  { "$value": { "colorSpace": "oklch", "components": [0.869, 0.018, 247], "hex": "#cbd5e1" } },
      "400":  { "$value": { "colorSpace": "oklch", "components": [0.706, 0.025, 257], "hex": "#94a3b8" } },
      "500":  { "$value": { "colorSpace": "oklch", "components": [0.553, 0.028, 257], "hex": "#64748b" } },
      "600":  { "$value": { "colorSpace": "oklch", "components": [0.444, 0.024, 257], "hex": "#475569" } },
      "700":  { "$value": { "colorSpace": "oklch", "components": [0.371, 0.020, 257], "hex": "#334155" } },
      "800":  { "$value": { "colorSpace": "oklch", "components": [0.279, 0.016, 257], "hex": "#1e293b" } },
      "900":  { "$value": { "colorSpace": "oklch", "components": [0.208, 0.013, 257], "hex": "#0f172a" } },
      "950":  { "$value": { "colorSpace": "oklch", "components": [0.145, 0.009, 257], "hex": "#020617" } },
      "1000": { "$value": { "colorSpace": "oklch", "components": [0, 0, "none"], "hex": "#000000" } }
    },
    "blue": {
      "50":  { "$value": { "colorSpace": "oklch", "components": [0.970, 0.014, 262], "hex": "#eff6ff" } },
      "100": { "$value": { "colorSpace": "oklch", "components": [0.938, 0.034, 262], "hex": "#dbeafe" } },
      "200": { "$value": { "colorSpace": "oklch", "components": [0.882, 0.066, 262], "hex": "#bfdbfe" } },
      "300": { "$value": { "colorSpace": "oklch", "components": [0.809, 0.113, 261], "hex": "#93c5fd" } },
      "400": { "$value": { "colorSpace": "oklch", "components": [0.707, 0.165, 261], "hex": "#60a5fa" } },
      "500": { "$value": { "colorSpace": "oklch", "components": [0.623, 0.214, 261], "hex": "#3b82f6" } },
      "600": { "$value": { "colorSpace": "oklch", "components": [0.546, 0.245, 262], "hex": "#2563eb" } },
      "700": { "$value": { "colorSpace": "oklch", "components": [0.467, 0.240, 264], "hex": "#1d4ed8" } },
      "800": { "$value": { "colorSpace": "oklch", "components": [0.392, 0.210, 265], "hex": "#1e40af" } },
      "900": { "$value": { "colorSpace": "oklch", "components": [0.332, 0.170, 265], "hex": "#1e3a8a" } },
      "950": { "$value": { "colorSpace": "oklch", "components": [0.237, 0.130, 265], "hex": "#172554" } }
    },
    "green": {
      "50":  { "$value": { "colorSpace": "oklch", "components": [0.971, 0.027, 155], "hex": "#f0fdf4" } },
      "100": { "$value": { "colorSpace": "oklch", "components": [0.945, 0.058, 155], "hex": "#dcfce7" } },
      "300": { "$value": { "colorSpace": "oklch", "components": [0.823, 0.149, 155], "hex": "#86efac" } },
      "400": { "$value": { "colorSpace": "oklch", "components": [0.740, 0.175, 155], "hex": "#4ade80" } },
      "500": { "$value": { "colorSpace": "oklch", "components": [0.650, 0.191, 155], "hex": "#22c55e" } },
      "600": { "$value": { "colorSpace": "oklch", "components": [0.528, 0.175, 155], "hex": "#16a34a" } },
      "700": { "$value": { "colorSpace": "oklch", "components": [0.437, 0.152, 155], "hex": "#15803d" } },
      "950": { "$value": { "colorSpace": "oklch", "components": [0.172, 0.062, 155], "hex": "#052e16" } }
    },
    "red": {
      "50":  { "$value": { "colorSpace": "oklch", "components": [0.971, 0.016, 24], "hex": "#fef2f2" } },
      "300": { "$value": { "colorSpace": "oklch", "components": [0.810, 0.137, 24], "hex": "#fca5a5" } },
      "400": { "$value": { "colorSpace": "oklch", "components": [0.703, 0.199, 27], "hex": "#f87171" } },
      "500": { "$value": { "colorSpace": "oklch", "components": [0.627, 0.247, 27], "hex": "#ef4444" } },
      "600": { "$value": { "colorSpace": "oklch", "components": [0.535, 0.252, 27], "hex": "#dc2626" } },
      "700": { "$value": { "colorSpace": "oklch", "components": [0.451, 0.228, 27], "hex": "#b91c1c" } },
      "950": { "$value": { "colorSpace": "oklch", "components": [0.196, 0.076, 27], "hex": "#450a0a" } }
    },
    "amber": {
      "50":  { "$value": { "colorSpace": "oklch", "components": [0.983, 0.025, 88], "hex": "#fffbeb" } },
      "300": { "$value": { "colorSpace": "oklch", "components": [0.893, 0.150, 88], "hex": "#fcd34d" } },
      "400": { "$value": { "colorSpace": "oklch", "components": [0.828, 0.182, 83], "hex": "#fbbf24" } },
      "500": { "$value": { "colorSpace": "oklch", "components": [0.769, 0.195, 79], "hex": "#f59e0b" } },
      "600": { "$value": { "colorSpace": "oklch", "components": [0.665, 0.187, 65], "hex": "#d97706" } },
      "700": { "$value": { "colorSpace": "oklch", "components": [0.558, 0.170, 55], "hex": "#b45309" } },
      "950": { "$value": { "colorSpace": "oklch", "components": [0.215, 0.066, 46], "hex": "#451a03" } }
    },
    "violet": {
      "50":  { "$value": { "colorSpace": "oklch", "components": [0.977, 0.020, 295], "hex": "#f5f3ff" } },
      "300": { "$value": { "colorSpace": "oklch", "components": [0.824, 0.139, 295], "hex": "#c4b5fd" } },
      "400": { "$value": { "colorSpace": "oklch", "components": [0.729, 0.201, 295], "hex": "#a78bfa" } },
      "500": { "$value": { "colorSpace": "oklch", "components": [0.627, 0.242, 295], "hex": "#8b5cf6" } },
      "600": { "$value": { "colorSpace": "oklch", "components": [0.541, 0.255, 295], "hex": "#7c3aed" } },
      "700": { "$value": { "colorSpace": "oklch", "components": [0.459, 0.241, 295], "hex": "#6d28d9" } },
      "950": { "$value": { "colorSpace": "oklch", "components": [0.193, 0.095, 295], "hex": "#2e1065" } }
    },
    "purple": {
      "100": { "$value": { "colorSpace": "oklch", "components": [0.910, 0.050, 275], "hex": "#d1d5ff" } },
      "200": { "$value": { "colorSpace": "oklch", "components": [0.780, 0.110, 275], "hex": "#a19dff" } },
      "300": { "$value": { "colorSpace": "oklch", "components": [0.620, 0.180, 275], "hex": "#6c47ff" } },
      "400": { "$value": { "colorSpace": "oklch", "components": [0.440, 0.200, 275], "hex": "#4417bf" } },
      "500": { "$value": { "colorSpace": "oklch", "components": [0.210, 0.160, 275], "hex": "#2b0160" } }
    },
    "pink": {
      "100": { "$value": { "colorSpace": "oklch", "components": [0.920, 0.050, 308], "hex": "#e9deff" } },
      "200": { "$value": { "colorSpace": "oklch", "components": [0.770, 0.130, 308], "hex": "#d191ff" } },
      "300": { "$value": { "colorSpace": "oklch", "components": [0.610, 0.220, 308], "hex": "#c247ff" } },
      "400": { "$value": { "colorSpace": "oklch", "components": [0.400, 0.220, 308], "hex": "#7b099e" } },
      "500": { "$value": { "colorSpace": "oklch", "components": [0.190, 0.140, 308], "hex": "#39003d" } }
    },
    "orange": {
      "100": { "$value": { "colorSpace": "oklch", "components": [0.940, 0.050, 35], "hex": "#ffdcd0" } },
      "200": { "$value": { "colorSpace": "oklch", "components": [0.840, 0.100, 35], "hex": "#feb9a7" } },
      "300": { "$value": { "colorSpace": "oklch", "components": [0.700, 0.160, 35], "hex": "#ff7f66" } },
      "400": { "$value": { "colorSpace": "oklch", "components": [0.490, 0.170, 35], "hex": "#cb4526" } },
      "500": { "$value": { "colorSpace": "oklch", "components": [0.210, 0.100, 35], "hex": "#471200" } }
    },
    "smartr-coral": {
      "$description": "SmartR brand coral. 500 = #FF6143 (brand spec). OKLCH L=0.693 C=0.197 H=33.",
      "50":  { "$value": { "colorSpace": "oklch", "components": [0.975, 0.015, 33], "hex": "#fff5f3" } },
      "100": { "$value": { "colorSpace": "oklch", "components": [0.945, 0.035, 33], "hex": "#ffd9d2" } },
      "300": { "$value": { "colorSpace": "oklch", "components": [0.820, 0.110, 33], "hex": "#ff9e8a" } },
      "400": { "$value": { "colorSpace": "oklch", "components": [0.760, 0.160, 33], "hex": "#ff7d66" } },
      "500": { "$value": { "colorSpace": "oklch", "components": [0.693, 0.197, 33], "hex": "#ff6143" } },
      "600": { "$value": { "colorSpace": "oklch", "components": [0.580, 0.190, 32], "hex": "#d93f25" } },
      "700": { "$value": { "colorSpace": "oklch", "components": [0.460, 0.160, 31], "hex": "#ac2d16" } },
      "950": { "$value": { "colorSpace": "oklch", "components": [0.165, 0.060, 29], "hex": "#400900" } }
    },
    "smartr-golden": {
      "$description": "SmartR brand golden. 500 = #FFD100 (brand spec). OKLCH L=0.875 C=0.180 H=91.",
      "50":  { "$value": { "colorSpace": "oklch", "components": [0.985, 0.012, 91], "hex": "#fffef0" } },
      "100": { "$value": { "colorSpace": "oklch", "components": [0.970, 0.035, 91], "hex": "#fffbcc" } },
      "300": { "$value": { "colorSpace": "oklch", "components": [0.945, 0.120, 91], "hex": "#fdf570" } },
      "400": { "$value": { "colorSpace": "oklch", "components": [0.920, 0.155, 91], "hex": "#fee523" } },
      "500": { "$value": { "colorSpace": "oklch", "components": [0.875, 0.180, 91], "hex": "#ffd100" } },
      "600": { "$value": { "colorSpace": "oklch", "components": [0.740, 0.160, 80], "hex": "#d49300" } },
      "700": { "$value": { "colorSpace": "oklch", "components": [0.580, 0.130, 70], "hex": "#976200" } },
      "950": { "$value": { "colorSpace": "oklch", "components": [0.185, 0.050, 65], "hex": "#231200" } }
    },
    "white":       { "$value": { "colorSpace": "oklch", "components": [1, 0, "none"], "hex": "#ffffff" } },
    "black":       { "$value": { "colorSpace": "oklch", "components": [0, 0, "none"], "hex": "#000000" } },
    "transparent": { "$value": { "colorSpace": "srgb", "components": [0, 0, 0], "alpha": 0, "hex": "#000000" } }
  }
}
